harmony_to_organoid/__init__.py
harmony_to_organoid/main.py
harmony_to_organoid/registration.py
harmony_to_organoid-0.5.0.dist-info/METADATA
harmony_to_organoid-0.5.0.dist-info/WHEEL
harmony_to_organoid-0.5.0.dist-info/entry_points.txt
harmony_to_organoid-0.5.0.dist-info/top_level.txt
harmony_to_organoid-0.5.0.dist-info/RECORD
