Metadata-Version: 2.2
Name: harmony-to-organoid
Version: 0.5.0
Summary: Utility for extracting individual organoid max projections from the export of Opera Phenix Harmony software.
Requires-Python: >=3.10
Requires-Dist: markdown==3.7
Requires-Dist: matplotlib==3.10.0
Requires-Dist: scikit-image==0.25.0
Requires-Dist: tifffile==2024.12.12
Requires-Dist: typer==0.15.1
Requires-Dist: imagecodecs>=2024.12.30
Requires-Dist: ashlar>=1.19.0
